<annotation>
    <folder>part3</folder>
    <filename>IMG_0180.jpg</filename>
    <size>
        <width>500</width>
        <height>375</height>
        <depth>3</depth>
    </size>
    <segmented>0</segmented>
    <object>
        <name>device</name>
        <pose>Unspecified</pose>
        <truncated>0</truncated>
        <difficult>0</difficult>
        <bndbox>
            <xmin>165</xmin>
            <ymin>70</ymin>
            <xmax>248</xmax>
            <ymax>207</ymax>
        </bndbox>
    </object>
    <object>
        <name>device</name>
        <pose>Unspecified</pose>
        <truncated>0</truncated>
        <difficult>0</difficult>
        <bndbox>
            <xmin>257</xmin>
            <ymin>119</ymin>
            <xmax>361</xmax>
            <ymax>220</ymax>
        </bndbox>
    </object>
    <object>
        <name>device</name>
        <pose>Unspecified</pose>
        <truncated>0</truncated>
        <difficult>0</difficult>
        <bndbox>
            <xmin>41</xmin>
            <ymin>126</ymin>
            <xmax>198</xmax>
            <ymax>324</ymax>
        </bndbox>
    </object>
</annotation>