<annotation>
    <folder>images</folder>
    <filename>68.jpg</filename>
    <size>
        <width>3024</width>
        <height>4032</height>
        <depth>3</depth>
    </size>
    <segmented>0</segmented>
    <object>
        <name>device</name>
        <pose>Unspecified</pose>
        <truncated>0</truncated>
        <difficult>0</difficult>
        <bndbox>
            <xmin>641</xmin>
            <ymin>99</ymin>
            <xmax>2549</xmax>
            <ymax>2831</ymax>
        </bndbox>
    </object>
</annotation>