<annotation>
    <folder>part4</folder>
    <filename>photo4_52.jpg</filename>
    <size>
        <width>2048</width>
        <height>1536</height>
        <depth>3</depth>
    </size>
    <segmented>0</segmented>
    <object>
        <name>device</name>
        <pose>Unspecified</pose>
        <truncated>0</truncated>
        <difficult>0</difficult>
        <bndbox>
            <xmin>951</xmin>
            <ymin>702</ymin>
            <xmax>1027</xmax>
            <ymax>814</ymax>
        </bndbox>
    </object>
    <object>
        <name>device</name>
        <pose>Unspecified</pose>
        <truncated>0</truncated>
        <difficult>0</difficult>
        <bndbox>
            <xmin>1103</xmin>
            <ymin>749</ymin>
            <xmax>1218</xmax>
            <ymax>835</ymax>
        </bndbox>
    </object>
</annotation>